nnmdkit/__init__.py
nnmdkit/core/Job.py
nnmdkit/core/Lammps.py
nnmdkit/core/System.py
nnmdkit/core/__init__.py
nnmdkit/util/Shortcut.py
nnmdkit/util/Util.py
nnmdkit/util/__init__.py
NNMDKit-0.1.0.dist-info/LICENSE
NNMDKit-0.1.0.dist-info/METADATA
NNMDKit-0.1.0.dist-info/WHEEL
NNMDKit-0.1.0.dist-info/top_level.txt
NNMDKit-0.1.0.dist-info/RECORD
