Metadata-Version: 2.1
Name: NNMDKit
Version: 0.1.0
Summary: Automated generation of LAMMPS data and input files for polymer molecular dynamics simulations
Home-page: https://github.com/Ramprasad-Group/NNMDKit
Author: Kuan-Hsuan Shen
Author-email: kshen64@gatech.edu
License: UNKNOWN
Keywords: LAMMPS,polymer,SMILES
Platform: UNKNOWN
Classifier: Programming Language :: Python :: 3
Classifier: License :: OSI Approved :: MIT License
Classifier: Operating System :: OS Independent
License-File: LICENSE
